ast2json/__init__.py
ast2json/ast2json.py
ast2json/types.py
ast2json/py2/__init__.py
ast2json/py3/__init__.py
ast2json-0.2.1.dist-info/DESCRIPTION.rst
ast2json-0.2.1.dist-info/METADATA
ast2json-0.2.1.dist-info/RECORD
ast2json-0.2.1.dist-info/WHEEL
ast2json-0.2.1.dist-info/metadata.json
ast2json-0.2.1.dist-info/top_level.txt
test/__init__.py
test/test_api.py
