Metadata-Version: 2.0
Name: ast2json
Version: 0.2.1
Summary: convert a python source code into json-dumpable data (dict and lists with strings, ints, ...)
Home-page: https://github.com/Psycojoker/ast2json
Author: Laurent Peuch
Author-email: cortex@worlddomination.be
License: BSD
Keywords: ast
Platform: UNKNOWN
Classifier: Development Status :: 3 - Alpha
Classifier: Intended Audience :: Developers
Classifier: Programming Language :: Python :: 2
Classifier: Programming Language :: Python :: 3
